{
    "input_length" : 512,
    "output_length" : 6,
    "num_train_epochs" : 20,
    "output_dir" : "",
    "dataset" : "WNED",
    "dataset_version" : "full",
    "train_batch_size" : 64,
    "learning_rate" : 1e-3,
    "model" : "google/t5-large-ssm",
    "method": "models_baseline",
    "freeze_level": 0,
    "gradient_accumulation_steps" : 1,
    "ngpu" : 4,
    "num_workers" : 40,
    "resume_from_checkpoint" : null,
    "accelerator" : "ddp",
    "use_deepspeed" : false,
    "CUDA_VISIBLE_DEVICES" : "0,1,2,3",
    "wandb_log": false,
    "wandb_project": "continual_learning_finetuning",
    "wandb_run_name" : "T5_large_initial_wned_finetuning_baseline",
    "mode" : "finetune",
    "use_lr_scheduling" : false,
    "check_validation" : true,
    "checkpoint_path" : "T5_large_initial_AY2_finetuning_baseline/last.ckpt",
    "output_log" : "log/kilt/WNED/initial.csv"
}